labsync/__init__.py
labsync/fsevent.py
labsync/google_drive.py
labsync/init.py
labsync/listen.py
labsync/main.py
labsync/overleaf.py
labsync/server.py
labsync/sync.py
labsync/taskmanager.py
labsync/tb_update.py
labsync/template.py
labsync/tensorboard.py
labsync/utils.py
labsync/watchfs.py
labsync-0.2.dist-info/LICENSE
labsync-0.2.dist-info/METADATA
labsync-0.2.dist-info/WHEEL
labsync-0.2.dist-info/entry_points.txt
labsync-0.2.dist-info/top_level.txt
labsync-0.2.dist-info/RECORD
