Metadata-Version: 2.1
Name: labsync
Version: 0.2
Summary: Toolkit for synchronizing works with remote servers
Home-page: UNKNOWN
Author: Zhouxing Shi
Author-email: zhouxingshichn@gmail.com
License: GNU GPL v3
Platform: UNKNOWN
Requires-Python: >=3.7
License-File: LICENSE
Requires-Dist: watchdog (>=0.10)
Requires-Dist: flask (>=1.1)
Requires-Dist: appdirs (>=1.4)
Requires-Dist: oslo.concurrency (>=4.2)
Requires-Dist: pydrive (>=1.3)
Requires-Dist: httplib2 (==0.15)
Requires-Dist: google-api-core (>=2.2.2)
Requires-Dist: google-auth (>=2.3.3)
